stpreview/__init__.py
stpreview/__main__.py
stpreview/downsample.py
stpreview/image.py
stpreview-0.6.0.dist-info/licenses/LICENSE
stpreview-0.6.0.dist-info/METADATA
stpreview-0.6.0.dist-info/WHEEL
stpreview-0.6.0.dist-info/entry_points.txt
stpreview-0.6.0.dist-info/top_level.txt
stpreview-0.6.0.dist-info/RECORD
