Metadata-Version: 2.4
Name: stpreview
Version: 0.6.0
Summary: build downsampled previews of space telescope products
Author-email: Zach Burnett <zburnett@stsci.edu>
Project-URL: repository, https://github.com/spacetelescope/stpreview.git
Classifier: Intended Audience :: Science/Research
Classifier: Topic :: Scientific/Engineering :: Astronomy
Classifier: License :: OSI Approved :: BSD License
Classifier: Programming Language :: Python :: 3
Requires-Python: >=3.11
License-File: LICENSE
Requires-Dist: asdf
Requires-Dist: astropy
Requires-Dist: gwcs
Requires-Dist: matplotlib
Requires-Dist: numpy
Requires-Dist: scikit-image
Provides-Extra: test
Requires-Dist: pytest; extra == "test"
Requires-Dist: roman_datamodels; extra == "test"
Dynamic: license-file
